NiftyNet-0.6.0.dist-info/METADATA
NiftyNet-0.6.0.dist-info/RECORD
NiftyNet-0.6.0.dist-info/WHEEL
NiftyNet-0.6.0.dist-info/entry_points.txt
NiftyNet-0.6.0.dist-info/top_level.txt
niftynet/__init__.py
niftynet/application/__init__.py
niftynet/application/autoencoder_application.py
niftynet/application/base_application.py
niftynet/application/classification_application.py
niftynet/application/gan_application.py
niftynet/application/label_driven_registration.py
niftynet/application/regression_application.py
niftynet/application/segmentation_application.py
niftynet/contrib/__init__.py
niftynet/contrib/checkpoint_tools/__init__.py
niftynet/contrib/checkpoint_tools/rename_checkpoint_to_partial.py
niftynet/contrib/csv_reader/__init__.py
niftynet/contrib/csv_reader/class_seg_finnet.py
niftynet/contrib/csv_reader/classification_application.py
niftynet/contrib/csv_reader/csv_reader.py
niftynet/contrib/csv_reader/highres3dnet_features.py
niftynet/contrib/csv_reader/multitask_classifseg_application.py
niftynet/contrib/csv_reader/sampler_balanced_v2_csv.py
niftynet/contrib/csv_reader/sampler_csv_rows.py
niftynet/contrib/csv_reader/sampler_csvpatch.py
niftynet/contrib/csv_reader/sampler_grid_v2_csv.py
niftynet/contrib/csv_reader/sampler_linear_interpolate_v2_csv.py
niftynet/contrib/csv_reader/sampler_random_vector_v2_csv.py
niftynet/contrib/csv_reader/sampler_resize_v2_csv.py
niftynet/contrib/csv_reader/sampler_uniform_v2_csv.py
niftynet/contrib/csv_reader/sampler_weighted_v2_csv.py
niftynet/contrib/csv_reader/segmentation_application_patchsampler.py
niftynet/contrib/csv_reader/toynet_features.py
niftynet/contrib/csv_reader/applications_maybe/__init__.py
niftynet/contrib/csv_reader/applications_maybe/autoencoder_application.py
niftynet/contrib/csv_reader/applications_maybe/gan_application.py
niftynet/contrib/csv_reader/applications_maybe/label_driven_registration.py
niftynet/contrib/csv_reader/applications_maybe/regression_application.py
niftynet/contrib/csv_reader/applications_maybe/segmentation_application.py
niftynet/contrib/deep_boosted_regression/__init__.py
