Metadata-Version: 2.1
Name: NiftyNet
Version: 0.6.0
Summary: An open-source convolutional neural networks platform for research in medical image analysis and image-guided therapy
Home-page: http://niftynet.io/
Author: NiftyNet Consortium
Author-email: niftynet-team@googlegroups.com
License: Apache 2.0
Platform: UNKNOWN
Classifier: Development Status :: 3 - Alpha
Classifier: Intended Audience :: Developers
Classifier: Intended Audience :: Healthcare Industry
Classifier: Intended Audience :: Science/Research
Classifier: License :: OSI Approved :: Apache Software License
Classifier: Programming Language :: Python
Classifier: Programming Language :: Python :: 2
Classifier: Programming Language :: Python :: 3
Classifier: Topic :: Scientific/Engineering :: Artificial Intelligence
Classifier: Topic :: Scientific/Engineering :: Image Recognition
Classifier: Topic :: Scientific/Engineering :: Medical Science Apps.
Requires-Dist: six (>=1.10)
Requires-Dist: nibabel (>=2.1.0)
Requires-Dist: numpy (>=1.13.3)
Requires-Dist: scipy (>=0.18)
Requires-Dist: configparser
Requires-Dist: pandas
Requires-Dist: pillow
Requires-Dist: blinker
Requires-Dist: packaging
